CODING-STYLE.md
LICENSE
MANIFEST.in
NOTICE
README.md
setup.py
behave_cli/__init__.py
behave_cli/environment.py
behave_cli/log.py
behave_cli/vars.py
behave_cli.egg-info/PKG-INFO
behave_cli.egg-info/SOURCES.txt
behave_cli.egg-info/dependency_links.txt
behave_cli.egg-info/requires.txt
behave_cli.egg-info/top_level.txt
behave_cli/api/__init__.py
behave_cli/api/environment.py
behave_cli/api/mock.py
behave_cli/api/robohydra.py
behave_cli/api/steps.py
behave_cli/expect/__init__.py
behave_cli/expect/environment.py
behave_cli/expect/steps.py
behave_cli/files/__init__.py
behave_cli/files/environment.py
behave_cli/files/file.py
behave_cli/files/steps.py
behave_cli/netrc/__init__.py
behave_cli/netrc/environment.py
behave_cli/netrc/steps.py
behave_cli/s3mock/__init__.py
behave_cli/s3mock/environment.py
behave_cli/s3mock/steps.py
features/__init__.py
features/environment.py
features/expect.feature
features/data/__init__.py
features/data/main.py
features/steps/__init__.py