Metadata-Version: 1.1
Name: behave-cli
Version: 0.2
Summary: Longaccess BDD CLI step library
Home-page: https://github.com/longaccess/longaccess-behave/
Author: Konstantinos Koukopoulos
Author-email: kk@longaccess.com
License: Apache
Platform: UNKNOWN
Classifier: Development Status :: 4 - Beta
Classifier: Intended Audience :: Developers
Classifier: Intended Audience :: System Administrators
Classifier: Intended Audience :: Information Technology
Classifier: Natural Language :: English
Classifier: License :: OSI Approved :: Apache Software License
Classifier: Operating System :: OS Independent
Classifier: Programming Language :: Python
Classifier: Programming Language :: Python :: 2
Classifier: Programming Language :: Python :: 2.6
Classifier: Programming Language :: Python :: 2.7
Classifier: Topic :: Software Development :: Testing
